ai_serving/__init__.py
ai_serving/client/__init__.py
ai_serving/client/_py2_var.py
ai_serving/client/_py3_var.py
ai_serving/client/ai_redis_server.py
ai_serving/client/helper.py
ai_serving/client/protocol.py
ai_serving/client/cli/__init__.py
ai_serving_client-0.0.0.dist-info/METADATA
ai_serving_client-0.0.0.dist-info/WHEEL
ai_serving_client-0.0.0.dist-info/top_level.txt
ai_serving_client-0.0.0.dist-info/RECORD
